setup.py
vrag/__init__.py
vrag/directory.py
vrag.egg-info/PKG-INFO
vrag.egg-info/SOURCES.txt
vrag.egg-info/dependency_links.txt
vrag.egg-info/requires.txt
vrag.egg-info/top_level.txt
vrag/data/__init__.py
vrag/data/dataset.py
vrag/data/video_loader.py
vrag/data/datasets/__init__.py
vrag/data/datasets/ccweb_video.py
vrag/data/datasets/evve.py
vrag/data/datasets/fivr200k.py
vrag/data/datasets/fivr5k.py
vrag/data/datasets/train.py
vrag/data/datasets/vcdb.py
vrag/data/datasets/vcdb_distractors.py
vrag/nets/__init__.py
vrag/nets/loss.py
vrag/nets/network.py
vrag/nets/rmac.py
vrag/scripts/__init__.py
vrag/scripts/create_video_embeddings.py
vrag/scripts/create_video_shot_embeddings.py
vrag/scripts/evaluate_evve_aqe.py
vrag/scripts/evaluate_video_embeddings.py
vrag/scripts/evaluate_video_shot_embeddings.py
vrag/scripts/extract_rmac_features.py
vrag/scripts/train.py
vrag/utils/__init__.py
vrag/utils/augment.py
vrag/utils/extract_fivr5k_frame_features.py
vrag/utils/shot_boundary_detection.py