Metadata-Version: 1.0
Name: vrag
Version: 0.0.2
Summary: vrag
Home-page: https://github.com/Kennard123661/VRAG
Author: kennardng
Author-email: e0036319@u.nus.edu
License: MIT License
Platform: UNKNOWN
